mcp_latest_document/__init__.py
mcp_latest_document/__main__.py
mcp_latest_document/server.py
mcp_latest_document-0.1.2.dist-info/METADATA
mcp_latest_document-0.1.2.dist-info/WHEEL
mcp_latest_document-0.1.2.dist-info/entry_points.txt
mcp_latest_document-0.1.2.dist-info/RECORD
